{
    "keep": {
        "days": true,
        "amount": 14
    },
    "auditLog": "F:\\Level 2\\practice\\university-project\\logs\\winston\\errors\\.fb7454d627891c12183abd500bbcf21d5f0f5caf-audit.json",
    "files": [
        {
            "date": 1692335157187,
            "name": "F:\\Level 2\\practice\\university-project\\logs\\winston\\errors\\uni-2023-08-18-11-success.log",
            "hash": "f256752b1d042078ba04821a9bea9bcceb92b1e9cb7ac1d643f1b008bae98d5e"
        },
        {
            "date": 1692340216860,
            "name": "F:\\Level 2\\practice\\university-project\\logs\\winston\\errors\\uni-2023-08-18-12-success.log",
            "hash": "5297f9a09e220cc3d3ab93e5dc57a71a7bbeb1e78e4369272ea1a4d1869b60cd"
        },
        {
            "date": 1692360327636,
            "name": "F:\\Level 2\\practice\\university-project\\logs\\winston\\errors\\uni-2023-08-18-18-success.log",
            "hash": "169230d64039010a8dc7ea3f31e2a2b18ad2bd8797bfc67c376a21437adc999d"
        }
    ],
    "hashType": "sha256"
}